{"inference_performance": 6.068276276204591, "timestamp": 1697767071, "done": false, "training_iteration": 1, "trial_id": "0315cda3", "date": "2023-10-19_18-57-51", "time_this_iter_s": 14.733101844787598, "time_total_s": 14.733101844787598, "pid": 23451, "hostname": "marsdengpu", "node_ip": "171.65.93.126", "config": {"lr": 0.010257424577883827, "lr_decay": 0.09120897248108631, "batch_size": 20, "latent_size_mlp": 2, "hl_mlp": 1}, "time_since_restore": 14.733101844787598, "iterations_since_restore": 1, "checkpoint_dir_name": null}
