{"inference_performance": 4.683474229174608, "timestamp": 1703670481, "done": false, "training_iteration": 1, "trial_id": "9aa2227c", "date": "2023-12-27_01-48-01", "time_this_iter_s": 61.18683433532715, "time_total_s": 61.18683433532715, "pid": 24118, "hostname": "marsdengpu", "node_ip": "171.65.93.126", "config": {"lr": 0.00015328593659658877, "lr_decay": 0.0037679189908429275, "batch_size": 23, "latent_size_mlp": 72, "hl_mlp": 1}, "time_since_restore": 61.18683433532715, "iterations_since_restore": 1, "checkpoint_dir_name": null}
