{"inference_performance": 2.032838756274919, "timestamp": 1697852619, "done": false, "training_iteration": 1, "trial_id": "5ed263fa", "date": "2023-10-20_18-43-39", "time_this_iter_s": 24.21874690055847, "time_total_s": 24.21874690055847, "pid": 12710, "hostname": "marsdengpu", "node_ip": "171.65.93.126", "config": {"lr": 0.01603283915970375, "lr_decay": 0.02004711814324016, "batch_size": 23, "latent_size_mlp": 46, "hl_mlp": 1}, "time_since_restore": 24.21874690055847, "iterations_since_restore": 1, "checkpoint_dir_name": null}
