{"inference_performance": 2.113683126771199, "timestamp": 1697854551, "done": false, "training_iteration": 1, "trial_id": "5ac7eea6", "date": "2023-10-20_19-15-51", "time_this_iter_s": 23.904478073120117, "time_total_s": 23.904478073120117, "pid": 12710, "hostname": "marsdengpu", "node_ip": "171.65.93.126", "config": {"lr": 0.013467037500532773, "lr_decay": 0.004962688473323316, "batch_size": 22, "latent_size_mlp": 47, "hl_mlp": 1}, "time_since_restore": 23.904478073120117, "iterations_since_restore": 1, "checkpoint_dir_name": null}
