{"inference_performance": 1.87618176777458, "timestamp": 1701718539, "done": false, "training_iteration": 1, "trial_id": "d6615d31", "date": "2023-12-04_11-35-39", "time_this_iter_s": 55.37671875953674, "time_total_s": 55.37671875953674, "pid": 17604, "hostname": "marsdengpu", "node_ip": "171.65.93.126", "config": {"lr": 0.11943767442172572, "lr_decay": 0.001188917852703732, "batch_size": 15, "latent_size_mlp": 40, "hl_mlp": 2}, "time_since_restore": 55.37671875953674, "iterations_since_restore": 1, "checkpoint_dir_name": null}
