{"inference_performance": 2.0436068486097416, "timestamp": 1701719933, "done": false, "training_iteration": 1, "trial_id": "08ea42ef", "date": "2023-12-04_11-58-53", "time_this_iter_s": 33.4100604057312, "time_total_s": 33.4100604057312, "pid": 17604, "hostname": "marsdengpu", "node_ip": "171.65.93.126", "config": {"lr": 0.05906717398627375, "lr_decay": 0.02052610874956567, "batch_size": 27, "latent_size_mlp": 40, "hl_mlp": 2}, "time_since_restore": 33.4100604057312, "iterations_since_restore": 1, "checkpoint_dir_name": null}
