{"inference_performance": 6.309534236655216, "timestamp": 1703568395, "done": false, "training_iteration": 1, "trial_id": "86ad4926", "date": "2023-12-25_21-26-35", "time_this_iter_s": 45.733333587646484, "time_total_s": 45.733333587646484, "pid": 30624, "hostname": "marsdengpu", "node_ip": "171.65.93.126", "config": {"lr": 0.00010569364833971963, "lr_decay": 0.3093364044379348, "batch_size": 25, "latent_size_mlp": 48, "hl_mlp": 1}, "time_since_restore": 45.733333587646484, "iterations_since_restore": 1, "checkpoint_dir_name": null}
