{"inference_performance": 4.578766985166755, "timestamp": 1703656819, "done": false, "training_iteration": 1, "trial_id": "1651ef11", "date": "2023-12-26_22-00-19", "time_this_iter_s": 60.76540660858154, "time_total_s": 60.76540660858154, "pid": 24118, "hostname": "marsdengpu", "node_ip": "171.65.93.126", "config": {"lr": 0.0005763557706576964, "lr_decay": 0.00041004541367499204, "batch_size": 25, "latent_size_mlp": 61, "hl_mlp": 1}, "time_since_restore": 60.76540660858154, "iterations_since_restore": 1, "checkpoint_dir_name": null}
