{"inference_performance": 4.589118619795775, "timestamp": 1703664402, "done": false, "training_iteration": 1, "trial_id": "81cc8020", "date": "2023-12-27_00-06-42", "time_this_iter_s": 68.14155721664429, "time_total_s": 68.14155721664429, "pid": 24118, "hostname": "marsdengpu", "node_ip": "171.65.93.126", "config": {"lr": 0.0010819237042304275, "lr_decay": 0.00013570910838574078, "batch_size": 21, "latent_size_mlp": 50, "hl_mlp": 1}, "time_since_restore": 68.14155721664429, "iterations_since_restore": 1, "checkpoint_dir_name": null}
