{"inference_performance": 4.54110896504882, "timestamp": 1703660045, "done": false, "training_iteration": 1, "trial_id": "b6a0aa4b", "date": "2023-12-26_22-54-05", "time_this_iter_s": 60.71035623550415, "time_total_s": 60.71035623550415, "pid": 24118, "hostname": "marsdengpu", "node_ip": "171.65.93.126", "config": {"lr": 0.0011009748010776278, "lr_decay": 0.0007061896256909479, "batch_size": 25, "latent_size_mlp": 46, "hl_mlp": 1}, "time_since_restore": 60.71035623550415, "iterations_since_restore": 1, "checkpoint_dir_name": null}
