{"inference_performance": 2.0173735311914776, "timestamp": 1697863196, "done": false, "training_iteration": 1, "trial_id": "400882ee", "date": "2023-10-20_21-39-56", "time_this_iter_s": 24.075974225997925, "time_total_s": 24.075974225997925, "pid": 12710, "hostname": "marsdengpu", "node_ip": "171.65.93.126", "config": {"lr": 0.01866637399194763, "lr_decay": 0.0473681966165241, "batch_size": 24, "latent_size_mlp": 41, "hl_mlp": 1}, "time_since_restore": 24.075974225997925, "iterations_since_restore": 1, "checkpoint_dir_name": null}
