{"inference_performance": 2.1799506067163907, "timestamp": 1697764689, "done": false, "training_iteration": 1, "trial_id": "279f41c7", "date": "2023-10-19_18-18-09", "time_this_iter_s": 16.33097767829895, "time_total_s": 16.33097767829895, "pid": 23451, "hostname": "marsdengpu", "node_ip": "171.65.93.126", "config": {"lr": 0.0494413227017085, "lr_decay": 0.032069755413888595, "batch_size": 19, "latent_size_mlp": 44, "hl_mlp": 1}, "time_since_restore": 16.33097767829895, "iterations_since_restore": 1, "checkpoint_dir_name": null}
