{"inference_performance": 1.9282568931138062, "timestamp": 1697862648, "done": false, "training_iteration": 1, "trial_id": "032abb54", "date": "2023-10-20_21-30-48", "time_this_iter_s": 32.331369161605835, "time_total_s": 32.331369161605835, "pid": 12710, "hostname": "marsdengpu", "node_ip": "171.65.93.126", "config": {"lr": 0.011015893997362419, "lr_decay": 0.03680522351377361, "batch_size": 17, "latent_size_mlp": 49, "hl_mlp": 1}, "time_since_restore": 32.331369161605835, "iterations_since_restore": 1, "checkpoint_dir_name": null}
