{"inference_performance": 4.618773695677057, "timestamp": 1703649043, "done": false, "training_iteration": 1, "trial_id": "49f15754", "date": "2023-12-26_19-50-43", "time_this_iter_s": 49.81771492958069, "time_total_s": 49.81771492958069, "pid": 24118, "hostname": "marsdengpu", "node_ip": "171.65.93.126", "config": {"lr": 0.0004770706039609206, "lr_decay": 0.009638127204156443, "batch_size": 30, "latent_size_mlp": 43, "hl_mlp": 2}, "time_since_restore": 49.81771492958069, "iterations_since_restore": 1, "checkpoint_dir_name": null}
