{"inference_performance": 1.9833049262215894, "timestamp": 1697864377, "done": false, "training_iteration": 1, "trial_id": "77159669", "date": "2023-10-20_21-59-37", "time_this_iter_s": 24.049828052520752, "time_total_s": 24.049828052520752, "pid": 12710, "hostname": "marsdengpu", "node_ip": "171.65.93.126", "config": {"lr": 0.023709415604337647, "lr_decay": 0.004462677217291508, "batch_size": 24, "latent_size_mlp": 52, "hl_mlp": 1}, "time_since_restore": 24.049828052520752, "iterations_since_restore": 1, "checkpoint_dir_name": null}
