{"inference_performance": 1.8998279084317442, "timestamp": 1697763823, "done": false, "training_iteration": 1, "trial_id": "7e0a2596", "date": "2023-10-19_18-03-43", "time_this_iter_s": 13.418036699295044, "time_total_s": 13.418036699295044, "pid": 23451, "hostname": "marsdengpu", "node_ip": "171.65.93.126", "config": {"lr": 0.02114965982800664, "lr_decay": 0.004958354662554889, "batch_size": 22, "latent_size_mlp": 47, "hl_mlp": 1}, "time_since_restore": 13.418036699295044, "iterations_since_restore": 1, "checkpoint_dir_name": null}
