{"inference_performance": 1.9785129044850815, "timestamp": 1697862672, "done": false, "training_iteration": 1, "trial_id": "7bf9b673", "date": "2023-10-20_21-31-12", "time_this_iter_s": 24.17963671684265, "time_total_s": 24.17963671684265, "pid": 12710, "hostname": "marsdengpu", "node_ip": "171.65.93.126", "config": {"lr": 0.01002809459936256, "lr_decay": 0.01585148844748046, "batch_size": 24, "latent_size_mlp": 42, "hl_mlp": 1}, "time_since_restore": 24.17963671684265, "iterations_since_restore": 1, "checkpoint_dir_name": null}
