{"inference_performance": 4.582549833866883, "timestamp": 1703676055, "done": false, "training_iteration": 1, "trial_id": "e2d8eb92", "date": "2023-12-27_03-20-55", "time_this_iter_s": 60.786874294281006, "time_total_s": 60.786874294281006, "pid": 24118, "hostname": "marsdengpu", "node_ip": "171.65.93.126", "config": {"lr": 3.612803575722884e-05, "lr_decay": 0.06993057249431754, "batch_size": 22, "latent_size_mlp": 54, "hl_mlp": 1}, "time_since_restore": 60.786874294281006, "iterations_since_restore": 1, "checkpoint_dir_name": null}
