{"inference_performance": 2.193642038611439, "timestamp": 1697764453, "done": false, "training_iteration": 1, "trial_id": "a3ed6095", "date": "2023-10-19_18-14-13", "time_this_iter_s": 11.772239208221436, "time_total_s": 11.772239208221436, "pid": 23451, "hostname": "marsdengpu", "node_ip": "171.65.93.126", "config": {"lr": 0.013089158582913162, "lr_decay": 0.003909696727295172, "batch_size": 22, "latent_size_mlp": 47, "hl_mlp": 0}, "time_since_restore": 11.772239208221436, "iterations_since_restore": 1, "checkpoint_dir_name": null}
