{"inference_performance": 6.2887827011878015, "timestamp": 1703574639, "done": false, "training_iteration": 1, "trial_id": "f9b793ef", "date": "2023-12-25_23-10-39", "time_this_iter_s": 40.49097919464111, "time_total_s": 40.49097919464111, "pid": 30624, "hostname": "marsdengpu", "node_ip": "171.65.93.126", "config": {"lr": 0.004167674933811587, "lr_decay": 0.3838701780188479, "batch_size": 26, "latent_size_mlp": 56, "hl_mlp": 1}, "time_since_restore": 40.49097919464111, "iterations_since_restore": 1, "checkpoint_dir_name": null}
