{"inference_performance": 1.9994251634009068, "timestamp": 1701720784, "done": false, "training_iteration": 1, "trial_id": "9794e072", "date": "2023-12-04_12-13-04", "time_this_iter_s": 37.64386010169983, "time_total_s": 37.64386010169983, "pid": 17604, "hostname": "marsdengpu", "node_ip": "171.65.93.126", "config": {"lr": 0.06355665921513208, "lr_decay": 0.012174972161968601, "batch_size": 25, "latent_size_mlp": 42, "hl_mlp": 2}, "time_since_restore": 37.64386010169983, "iterations_since_restore": 1, "checkpoint_dir_name": null}
